plugin/__init__.py
plugin/emoji.py
pytest_emoji_output-0.2.1.dist-info/AUTHORS.md
pytest_emoji_output-0.2.1.dist-info/LICENSE.md
pytest_emoji_output-0.2.1.dist-info/METADATA
pytest_emoji_output-0.2.1.dist-info/WHEEL
pytest_emoji_output-0.2.1.dist-info/entry_points.txt
pytest_emoji_output-0.2.1.dist-info/top_level.txt
pytest_emoji_output-0.2.1.dist-info/RECORD
