Metadata-Version: 2.1
Name: pytest-emoji-output
Version: 0.2.1
Summary: Pytest plugin to represent test output with emoji support
Home-page: https://github.com/vyahello/pytest-emoji-output
Author: Volodymyr Yahello
Author-email: vyahello@gmail.com
Maintainer: Volodymyr Yahello
Maintainer-email: vyahello@gmail.com
License: MIT
Classifier: Development Status :: 4 - Beta
Classifier: Framework :: Pytest
Classifier: Intended Audience :: Developers
Classifier: Topic :: Software Development :: Testing
Classifier: Programming Language :: Python
Classifier: Programming Language :: Python :: 3.7
Classifier: Programming Language :: Python :: 3.8
Classifier: Programming Language :: Python :: 3.9
Classifier: Programming Language :: Python :: 3.10
Classifier: Programming Language :: Python :: Implementation :: CPython
Classifier: Operating System :: OS Independent
Classifier: License :: OSI Approved :: MIT License
Requires-Python: >=3.6
License-File: LICENSE.md
License-File: AUTHORS.md
Requires-Dist: attrs (==19.3.0)
Requires-Dist: click (==8.0.4)
Requires-Dist: pytest (==7.0.1)
